nyxploit/__init__.py
nyxploit-0.0.1.dist-info/licenses/LICENSE
nyxploit-0.0.1.dist-info/METADATA
nyxploit-0.0.1.dist-info/WHEEL
nyxploit-0.0.1.dist-info/top_level.txt
nyxploit-0.0.1.dist-info/RECORD
