Metadata-Version: 2.4
Name: nyxploit
Version: 0.0.1
Summary: Namespace reservation for Nyxploit
Author: Sean Richardson
Author-email: sean@nyxploit.com
Classifier: Programming Language :: Python :: 3
Classifier: License :: OSI Approved :: MIT License
Classifier: Operating System :: OS Independent
Requires-Python: >=3.6
License-File: LICENSE
Dynamic: author
Dynamic: author-email
Dynamic: classifier
Dynamic: license-file
Dynamic: requires-python
Dynamic: summary
